kubernetes_validate
