Metadata-Version: 2.4
Name: kubernetes-validate
Version: 1.33.0
Summary: validates kubernetes resource definitions against schemas
Author-email: Will Thames <will@thames.id.au>
License: Apache
Project-URL: Homepage, https://github.com/willthames/kubernetes-validate
Keywords: kubernetes,schema,validate,validator
Requires-Python: >=3.7
License-File: LICENSE
Requires-Dist: PyYAML
Requires-Dist: jsonschema
Requires-Dist: typing-extensions
Requires-Dist: importlib-resources
Requires-Dist: packaging
Requires-Dist: referencing
Dynamic: license-file
